setup.py
distributions/Binomialdistribution.py
distributions/Gaussiandistribution.py
distributions/Generaldistribution.py
distributions/__init__.py
gaussbnprobs.egg-info/PKG-INFO
gaussbnprobs.egg-info/SOURCES.txt
gaussbnprobs.egg-info/dependency_links.txt
gaussbnprobs.egg-info/not-zip-safe
gaussbnprobs.egg-info/top_level.txt